bear_model/__init__.py
bear_model/_version.py
bear_model/ar_funcs.py
bear_model/bear_net.py
bear_model/bear_ref.py
bear_model/core.py
bear_model/dataloader.py
bear_model/tests/__init__.py
bear_model/tests/conftest.py
bear_model/tests/test_core.py
bear_model/tests/test_dataloader.py
bear_model/tests/test_run.py
bear_model-0.1.0.dist-info/AUTHORS.rst
bear_model-0.1.0.dist-info/LICENSE
bear_model-0.1.0.dist-info/METADATA
bear_model-0.1.0.dist-info/WHEEL
bear_model-0.1.0.dist-info/entry_points.txt
bear_model-0.1.0.dist-info/top_level.txt
bear_model-0.1.0.dist-info/RECORD
